slack_pull_reminder.py
slack_pull_reminder-0.2.0.dist-info/LICENSE
slack_pull_reminder-0.2.0.dist-info/METADATA
slack_pull_reminder-0.2.0.dist-info/WHEEL
slack_pull_reminder-0.2.0.dist-info/entry_points.txt
slack_pull_reminder-0.2.0.dist-info/top_level.txt
slack_pull_reminder-0.2.0.dist-info/RECORD
