Metadata-Version: 2.1
Name: slack-pull-reminder
Version: 0.2.0
Summary: Posts a Slack reminder with a list of open pull requests for an organization
Home-page: http://github.com/ekmartin/slack-pull-reminder
Author: Martin Ek
Author-email: mail@ekmartin.com
License: MIT
Platform: UNKNOWN
Requires-Dist: requests (==2.21.0)
Requires-Dist: github3.py (==1.0.0a4)
